[
  {
    "path": "posts/2022-10-07-entrega-ii-preparacion-de-los-datos/",
    "title": "Entrega II - Impacto de los cambios de los componentes ópticos oculares en la refracción de los jóvenes",
    "description": "En este post se presenta la primera fase del análisis de datos - preparación de datos - en la que se analizan las características de las variables y se procesa el tratamiento de los datos. Además, se realiza un análisis gráfico de los datos. [WIP]",
    "author": [
      {
        "name": "Ines Pereira",
        "url": "https://example.com/norajones"
      }
    ],
    "date": "2022-10-07",
    "categories": [],
    "contents": "\r\nBase de datos\r\n\r\n\r\nlibrary(xlsx)\r\ndata <- read.xlsx(\"base_datos.xlsx\",1)\r\ndata <- data.frame(data)\r\nstr(data)\r\n\r\n'data.frame':   1150 obs. of  18 variables:\r\n $ id           : num  1 2 3 4 5 6 7 8 9 10 ...\r\n $ clase        : chr  \"7ºC\" \"7ºC\" \"7ºC\" \"7ºC\" ...\r\n $ nombre       : chr  \"João Pedro\" \"Francisco F.\" \"Francisco S.\" \"José Pereira\" ...\r\n $ sexo         : num  1 1 1 1 1 1 0 0 1 0 ...\r\n $ ametropia    : num  0 -1 1 0 0 1 1 0 1 0 ...\r\n $ edad         : num  13 13 12 13 12 12 13 12 12 12 ...\r\n $ grupo_etario : num  2 2 2 2 2 2 2 2 2 2 ...\r\n $ M            : num  0.29 -0.63 1 0.38 0.42 1.38 0.71 -0.46 0.67 -0.04 ...\r\n $ J0           : num  0.06 0.16 0.38 -0.23 0.05 -0.03 0.43 0.28 0.04 0.04 ...\r\n $ J45          : num  -0.1 0.14 -0.17 0.3 -0.06 -0.03 -0.14 -0.08 -0.24 -0.03 ...\r\n $ esf          : num  0.41 -0.42 1.41 0.75 0.5 1.42 1.17 -0.17 0.91 0.01 ...\r\n $ cil          : num  -0.24 -0.42 -0.83 -0.75 -0.17 -0.08 -0.92 -0.58 -0.49 -0.1 ...\r\n $ eje          : chr  \"151.35\" \"20.8\" \"167.9\" \"63.67\" ...\r\n $ orient_astigm: chr  \"2\" \"2\" \"1\" \"2\" ...\r\n $ esfera       : num  1 1 2 1 1 2 2 1 1 1 ...\r\n $ CA           : num  24.5 22.4 23.2 22.9 23.2 ...\r\n $ RC           : num  8.21 7.52 8.06 7.72 7.97 7.58 7.93 7.41 8.22 7.42 ...\r\n $ CA_RC_1      : num  2.99 2.99 2.88 2.96 2.92 ...\r\n\r\nCaracterísticas de las\r\nvariables\r\n\r\n\r\ndata$eje=as.numeric(data$eje)\r\ndata$orient_astigm=as.numeric(data$orient_astigm)\r\nstr(data)\r\n\r\n'data.frame':   1150 obs. of  18 variables:\r\n $ id           : num  1 2 3 4 5 6 7 8 9 10 ...\r\n $ clase        : chr  \"7ºC\" \"7ºC\" \"7ºC\" \"7ºC\" ...\r\n $ nombre       : chr  \"João Pedro\" \"Francisco F.\" \"Francisco S.\" \"José Pereira\" ...\r\n $ sexo         : num  1 1 1 1 1 1 0 0 1 0 ...\r\n $ ametropia    : num  0 -1 1 0 0 1 1 0 1 0 ...\r\n $ edad         : num  13 13 12 13 12 12 13 12 12 12 ...\r\n $ grupo_etario : num  2 2 2 2 2 2 2 2 2 2 ...\r\n $ M            : num  0.29 -0.63 1 0.38 0.42 1.38 0.71 -0.46 0.67 -0.04 ...\r\n $ J0           : num  0.06 0.16 0.38 -0.23 0.05 -0.03 0.43 0.28 0.04 0.04 ...\r\n $ J45          : num  -0.1 0.14 -0.17 0.3 -0.06 -0.03 -0.14 -0.08 -0.24 -0.03 ...\r\n $ esf          : num  0.41 -0.42 1.41 0.75 0.5 1.42 1.17 -0.17 0.91 0.01 ...\r\n $ cil          : num  -0.24 -0.42 -0.83 -0.75 -0.17 -0.08 -0.92 -0.58 -0.49 -0.1 ...\r\n $ eje          : num  151.3 20.8 167.9 63.7 154.5 ...\r\n $ orient_astigm: num  2 2 1 2 2 2 1 1 2 1 ...\r\n $ esfera       : num  1 1 2 1 1 2 2 1 1 1 ...\r\n $ CA           : num  24.5 22.4 23.2 22.9 23.2 ...\r\n $ RC           : num  8.21 7.52 8.06 7.72 7.97 7.58 7.93 7.41 8.22 7.42 ...\r\n $ CA_RC_1      : num  2.99 2.99 2.88 2.96 2.92 ...\r\n\r\nsummary(data)\r\n\r\n       id            clase              nombre         \r\n Min.   :   1.0   Length:1150        Length:1150       \r\n 1st Qu.: 288.2   Class :character   Class :character  \r\n Median : 575.5   Mode  :character   Mode  :character  \r\n Mean   : 575.5                                        \r\n 3rd Qu.: 862.8                                        \r\n Max.   :1150.0                                        \r\n                                                       \r\n      sexo          ametropia            edad        grupo_etario  \r\n Min.   :0.0000   Min.   :-1.0000   Min.   : 5.00   Min.   :1.000  \r\n 1st Qu.:0.0000   1st Qu.:-1.0000   1st Qu.:13.00   1st Qu.:2.000  \r\n Median :1.0000   Median : 0.0000   Median :18.07   Median :3.000  \r\n Mean   :0.5183   Mean   :-0.1148   Mean   :16.33   Mean   :2.505  \r\n 3rd Qu.:1.0000   3rd Qu.: 0.0000   3rd Qu.:18.57   3rd Qu.:3.000  \r\n Max.   :1.0000   Max.   : 1.0000   Max.   :38.09   Max.   :3.000  \r\n                                                                   \r\n       M                 J0                J45           \r\n Min.   :-8.8750   Min.   :-0.82983   Min.   :-2.054075  \r\n 1st Qu.:-0.7488   1st Qu.:-0.03474   1st Qu.:-0.084204  \r\n Median : 0.0250   Median : 0.09988   Median : 0.000000  \r\n Mean   :-0.5074   Mean   : 0.14836   Mean   : 0.009358  \r\n 3rd Qu.: 0.3950   3rd Qu.: 0.24750   3rd Qu.: 0.090324  \r\n Max.   : 7.8800   Max.   : 3.40089   Max.   : 3.929383  \r\n                   NA's   :4          NA's   :4          \r\n      esf              cil               eje         orient_astigm  \r\n Min.   :-8.380   Min.   :-7.9800   Min.   :  0.00   Min.   :1.000  \r\n 1st Qu.:-0.470   1st Qu.:-0.6678   1st Qu.: 23.00   1st Qu.:1.000  \r\n Median : 0.250   Median :-0.4200   Median : 89.00   Median :2.000  \r\n Mean   :-0.215   Mean   :-0.5870   Mean   : 89.44   Mean   :1.703  \r\n 3rd Qu.: 0.600   3rd Qu.:-0.2500   3rd Qu.:156.00   3rd Qu.:2.000  \r\n Max.   : 8.610   Max.   : 0.0000   Max.   :180.00   Max.   :3.000  \r\n                  NA's   :4         NA's   :10       NA's   :3      \r\n     esfera            CA              RC           CA_RC_1     \r\n Min.   :1.000   Min.   :20.15   Min.   :6.925   Min.   :2.590  \r\n 1st Qu.:1.000   1st Qu.:22.88   1st Qu.:7.595   1st Qu.:2.957  \r\n Median :1.000   Median :23.52   Median :7.785   Median :3.014  \r\n Mean   :1.286   Mean   :23.63   Mean   :7.799   Mean   :3.031  \r\n 3rd Qu.:2.000   3rd Qu.:24.23   3rd Qu.:7.971   3rd Qu.:3.081  \r\n Max.   :2.000   Max.   :27.70   Max.   :9.240   Max.   :3.558  \r\n                                                                \r\n\r\n##numerical variables with missing values: J0, J45, cil, eje, orient_astigm\r\n\r\n\r\nOutliers & Boxplots\r\n\r\n\r\n#see outliers of non-binary variables\r\n##variable edad\r\nboxplot(data$edad, col=\"lightblue\", main=\"Edad Boxplot\",\r\n        ylab=\"Edad\")\r\n\r\n\r\nboxplot.stats(data$edad)\r\n\r\n$stats\r\n[1]  5.00000 13.00000 18.07255 18.57358 26.46954\r\n\r\n$n\r\n[1] 1150\r\n\r\n$conf\r\n[1] 17.81287 18.33224\r\n\r\n$out\r\n [1] 27.35661 28.88433 30.54620 31.23888 33.48392 28.19165 36.49555\r\n [8] 33.36893 36.35044 34.38193 38.08898 26.99247\r\n\r\n##Variable M\r\nboxplot(data$M, col=\"lightgreen\", main=\"M Boxplot\",\r\n        ylab=\"M\")\r\n\r\n\r\nboxplot.stats(data$M)\r\n\r\n$stats\r\n[1] -2.450000 -0.750000  0.025000  0.395000  2.083333\r\n\r\n$n\r\n[1] 1150\r\n\r\n$conf\r\n[1] -0.02834745  0.07834745\r\n\r\n$out\r\n  [1] -4.040000 -4.420000 -3.210000 -4.170000 -4.920000 -2.880000\r\n  [7] -4.630000 -3.210000 -3.330000 -4.083333  3.750000 -3.041667\r\n [13] -2.750000 -3.208333 -5.000000 -3.083333 -3.750000  2.166667\r\n [19] -5.958333 -5.416667 -3.208333 -2.625000 -4.250000 -3.291667\r\n [25] -2.833333 -4.805000 -5.625000 -4.250000 -3.375000 -3.875000\r\n [31] -4.250000 -6.430000 -8.120000 -8.875000 -8.250000 -2.625000\r\n [37] -2.625000 -3.125000 -2.805000 -5.930000 -3.000000 -2.875000\r\n [43] -4.495000 -3.180000 -3.625000 -4.500000 -5.125000 -3.560000\r\n [49] -3.805000 -5.875000 -6.000000 -2.750000 -3.625000 -7.125000\r\n [55] -6.555000 -4.555000 -4.430000 -4.000000 -4.250000 -4.805000\r\n [61] -4.625000 -4.435000 -4.435000 -4.000000 -3.875000 -4.750000\r\n [67] -5.875000 -2.875000 -3.875000 -3.000000 -3.875000 -2.625000\r\n [73] -3.750000 -4.000000 -4.415000 -8.875000 -3.450000 -2.715000\r\n [79] -3.325000 -4.360000 -2.830000 -5.965000 -4.215000 -2.860000\r\n [85] -3.880000  7.880000 -4.490000 -4.710000  4.260000 -3.035000\r\n [91] -3.905000 -3.815000 -8.530000 -2.500000 -5.385000 -5.400000\r\n [97] -3.995000 -8.120000 -3.985000 -5.060000 -4.655000 -2.640000\r\n[103] -2.730000 -3.235000 -6.100000 -4.405000 -3.630000 -4.610000\r\n[109] -3.255000 -2.670000  2.310000 -3.590000 -2.725000 -3.960000\r\n[115] -6.480000  2.140000 -4.200000 -2.815000  3.415000 -3.090000\r\n[121] -5.575000 -5.800000 -3.430000 -3.550000 -5.025000  2.935000\r\n[127] -5.420000 -3.065000 -8.315000 -3.740000 -4.260000 -5.555000\r\n[133] -3.370000 -7.015000 -4.245000 -3.495000 -6.775000 -6.765000\r\n[139] -3.775000 -3.795000 -2.870000 -2.980000 -3.630000 -2.565000\r\n\r\n##Variable J0\r\nboxplot(data$J0, col=\"lightpink\", main=\"J0 Boxplot\",\r\n        ylab=\"J0\")\r\n\r\n\r\nboxplot.stats(data$J0)\r\n\r\n$stats\r\n[1] -0.44916613 -0.03491474  0.09987820  0.24751946  0.67082406\r\n\r\n$n\r\n[1] 1146\r\n\r\n$conf\r\n[1] 0.08669618 0.11306023\r\n\r\n$out\r\n [1]  1.5200000  0.9100000 -0.5300000  2.1200000  1.4000000  0.8200000\r\n [7]  0.8700000  1.7400000 -0.5000000  1.1600000 -0.4990865  1.4147999\r\n[13]  1.3660336  0.6947038  2.6892210  1.6643489  2.1107816  1.5660671\r\n[19]  0.9846853  0.8476300  0.7399897  0.7895105  0.8501408  1.4583333\r\n[25]  0.6831522  1.2456875  1.1591049  1.4836482  0.7495431  0.6845827\r\n[31]  0.8750000  1.2352213  0.8363162  0.9945531  1.3915092  1.0574179\r\n[37] -0.5650865  0.8335900  0.9318198  1.4491167  0.9127711  0.7386058\r\n[43] -0.6265488  0.8694700  1.3578558  1.0225032  0.9936590  1.0336619\r\n[49]  1.2200000  0.8717963  0.6928562  0.9100176  1.1896689  0.7993523\r\n[55]  1.0225032  2.5288249 -0.7731121  1.5039584  0.7545401  1.1690296\r\n[61]  1.2457818  0.6944848  1.8127363  3.4008865  0.7238337  0.7327984\r\n[67]  0.8036428  1.0298788 -0.8298295  1.7077087  1.1128328  1.1147172\r\n[73] -0.5168309  0.6799775  0.6830835  0.6745888\r\n\r\n##Variable J45\r\nboxplot(data$J45, col=\"violet\", main=\"J45 Boxplot\",\r\n        ylab=\"J45\")\r\n\r\n\r\nboxplot.stats(data$J45)\r\n\r\n$stats\r\n[1] -0.33921924 -0.08420423  0.00000000  0.09033263  0.34960675\r\n\r\n$n\r\n[1] 1146\r\n\r\n$conf\r\n[1] -0.008146142  0.008146142\r\n\r\n$out\r\n [1] -0.3600000 -1.9200000 -0.3512506  0.7393946 -0.5407797 -2.0540749\r\n [7]  0.4493970 -0.3604731 -0.9612617  0.5300301  0.5300301 -0.4820665\r\n[13] -0.6007886 -0.3673658 -0.4300000 -0.3541940  0.4937942  1.0109906\r\n[19]  0.6336498  0.8632078  0.4951566 -0.5071006  0.3764796 -0.3973923\r\n[25]  0.4382395 -0.3509270 -0.3943424  0.8353274 -0.9742786  0.4719838\r\n[31] -0.3836891  0.3847655  0.5222937 -0.3896477 -0.4012982  0.3882568\r\n[37]  0.4186362  0.4942191 -0.3497868  1.1035701  0.3762222  0.3897114\r\n[43] -0.6284654 -0.4359151  0.3881183  0.3973923  0.3751155  0.9027714\r\n[49]  3.9293829  1.0106770  0.8024418  0.4634569 -0.4037712  0.3558946\r\n[55] -0.3749789  0.8493497  1.7505391  0.8479362  0.4279754  0.4061559\r\n[61]  0.8329052  0.5821436  1.0036959 -0.3709120 -0.4316039 -0.6122545\r\n\r\n##Variable esf\r\nboxplot(data$esf, col=\"orange\", main=\"Esfera Boxplot\",\r\n        ylab=\"Esfera\")\r\n\r\n\r\nboxplot.stats(data$esf)\r\n\r\n$stats\r\n[1] -2.07 -0.47  0.25  0.60  2.14\r\n\r\n$n\r\n[1] 1150\r\n\r\n$conf\r\n[1] 0.2001469 0.2998531\r\n\r\n$out\r\n  [1] -2.190000 -3.670000 -4.340000 -2.840000  2.500000 -3.580000\r\n  [7]  4.250000 -4.770000 -2.110000 -2.330000 -2.090000 -4.340000\r\n [13] -3.100000 -3.160000 -3.836240  2.324644  4.084127  3.416084\r\n [19] -2.918353  3.164192  2.240460  4.164017 -2.667288 -2.916841\r\n [25] -4.750000 -2.836067  2.750000 -3.593860  4.749647 -5.676606\r\n [31] -4.417046 -2.583418 -2.336514 -4.000190 -3.182402 -2.667092\r\n [37] -4.620000 -5.500000 -3.750000 -2.750000 -3.750000 -3.750000\r\n [43] -5.870000 -7.120000 -8.250000 -7.750000 -2.250000 -2.250000\r\n [49] -2.750000 -4.370000 -2.250000 -2.250000 -4.370000 -3.120000\r\n [55] -3.250000 -4.250000 -5.000000 -3.000000 -3.120000 -5.750000\r\n [61] -5.750000 -2.750000 -3.250000 -7.000000 -6.120000 -4.370000\r\n [67] -4.120000 -3.750000 -4.250000 -4.370000 -4.000000 -4.000000\r\n [73] -4.000000 -4.000000 -3.750000 -4.250000 -5.000000 -2.250000\r\n [79] -3.500000 -2.750000 -3.500000 -2.250000 -3.750000 -3.750000\r\n [85] -4.150000 -8.380000 -2.180000 -3.050000 -2.630000 -3.020000\r\n [91] -4.180000 -2.190000 -5.600000 -3.950000 -2.550000 -3.710000\r\n [97]  8.610000 -4.170000 -4.500000  4.470000 -2.620000 -2.900000\r\n[103] -3.380000  2.540000 -8.080000 -2.240000 -4.400000 -5.210000\r\n[109] -3.740000 -7.750000 -3.640000 -2.220000 -4.900000 -4.440000\r\n[115] -2.370000 -2.560000 -5.230000 -2.110000 -3.950000 -3.490000\r\n[121] -4.370000 -3.160000  2.460000 -2.370000  3.530000 -3.400000\r\n[127] -2.340000 -3.590000 -5.920000  2.770000 -2.140000 -3.510000\r\n[133] -2.760000  3.970000 -5.440000 -4.440000 -3.090000 -3.200000\r\n[139] -4.580000  3.810000 -5.410000  2.350000 -5.780000 -3.730000\r\n[145] -3.670000 -4.110000  2.610000 -3.030000  2.760000 -3.510000\r\n[151] -4.240000 -3.270000 -5.930000 -6.140000 -2.880000 -3.770000\r\n[157] -2.190000  3.080000 -2.750000 -3.080000 -2.500000\r\n\r\n##Variable cil\r\nboxplot(data$cil, col=\"lightyellow\", main=\"Cilindro Boxplot\",\r\n        ylab=\"Cilindro\")\r\n\r\n\r\nboxplot.stats(data$cil)\r\n\r\n$stats\r\n[1] -1.2800000 -0.6682549 -0.4200000 -0.2500000  0.0000000\r\n\r\n$n\r\n[1] 1146\r\n\r\n$conf\r\n[1] -0.4395212 -0.4004788\r\n\r\n$out\r\n [1] -3.080000 -1.920000 -4.250000 -4.750000 -1.660000 -1.410000\r\n [7] -1.750000 -3.500000 -2.330000 -2.915501 -2.745051 -1.397586\r\n[13] -5.578033 -3.500000 -1.416470 -4.235627 -5.165962 -1.999241\r\n[19] -1.747158 -1.579216 -1.582676 -1.742663 -2.916667 -1.416470\r\n[25] -2.499662 -2.000000 -2.370000 -3.120000 -1.500000 -1.370000\r\n[31] -1.750000 -2.570000 -1.710000 -2.050000 -1.350000 -3.440000\r\n[37] -1.410000 -2.120000 -2.400000 -1.480000 -1.460000 -2.010000\r\n[43] -2.900000 -1.830000 -1.970000 -2.250000 -1.500000 -1.580000\r\n[49] -1.350000 -1.330000 -1.740000 -2.890000 -1.310000 -2.050000\r\n[55] -2.970000 -2.200000 -2.440000 -1.380000 -2.510000 -7.980000\r\n[61] -2.720000 -2.870000 -1.750000 -1.320000 -1.340000 -2.050000\r\n[67] -5.070000 -1.550000 -3.100000 -1.510000 -2.890000 -2.530000\r\n[73] -1.420000 -5.040000 -7.010000 -1.470000 -1.480000 -1.690000\r\n[79] -2.080000 -1.790000 -3.800000 -1.740000 -2.260000 -1.460000\r\n[85] -3.000000 -1.830000 -1.520000 -1.350000\r\n\r\n##Variable eje\r\nboxplot(data$eje, col=\"#3391FF\", main=\"Eje Boxplot\",\r\n        ylab=\"Eje\")\r\n\r\n\r\nboxplot.stats(data$eje)\r\n\r\n$stats\r\n[1]   0  23  89 156 180\r\n\r\n$n\r\n[1] 1140\r\n\r\n$conf\r\n[1] 82.77619 95.22381\r\n\r\n$out\r\nnumeric(0)\r\n\r\n##Variable CA\r\nboxplot(data$CA, col=\"#CBF4A9\", main=\"Longitud del Ojo Boxplot\",\r\n        ylab=\"CA\")\r\n\r\n\r\nboxplot.stats(data$CA)\r\n\r\n$stats\r\n[1] 20.90 22.88 23.52 24.23 26.17\r\n\r\n$n\r\n[1] 1150\r\n\r\n$conf\r\n[1] 23.4571 23.5829\r\n\r\n$out\r\n [1] 26.26 20.15 26.36 26.52 26.31 26.33 26.28 27.11 27.17 27.70 26.27\r\n[12] 26.36 26.95 26.64 26.33 27.08 26.74 26.63 26.45 26.90 26.29 26.98\r\n[23] 26.34 26.68 20.68\r\n\r\n##Variable RC\r\nboxplot(data$RC, col=\"#B7F6DA\", main=\"Radio de Curvatura Boxplot\",\r\n        ylab=\"RC\")\r\n\r\n\r\nboxplot.stats(data$RC)\r\n\r\n$stats\r\n[1] 7.055000 7.595000 7.785000 7.971665 8.535000\r\n\r\n$n\r\n[1] 1150\r\n\r\n$conf\r\n[1] 7.767451 7.802549\r\n\r\n$out\r\n [1] 9.235 8.575 8.840 8.645 8.585 8.600 8.550 8.680 8.630 8.620 8.785\r\n[12] 9.240 6.925 8.680 9.155\r\n\r\n##Variable CA_RC_1\r\nboxplot(data$CA_RC_1, col=\"#F6B7B7\", main=\"CA_RC_1 Boxplot\",\r\n        ylab=\"CA_RC_1\")\r\n\r\n\r\nboxplot.stats(data$CA_RC_1)\r\n\r\n$stats\r\n[1] 2.774036 2.957317 3.013626 3.081188 3.264911\r\n\r\n$n\r\n[1] 1150\r\n\r\n$conf\r\n[1] 3.007855 3.019397\r\n\r\n$out\r\n [1] 3.274314 2.731288 2.718848 2.672259 2.677741 2.744246 2.769821\r\n [8] 3.292942 3.391989 3.287396 3.394523 3.276425 3.446705 3.500902\r\n[15] 3.531025 3.503064 3.286037 3.364659 3.364058 3.301440 3.295948\r\n[22] 3.280267 3.269502 3.348412 3.399365 3.303189 3.359929 3.281161\r\n[29] 3.558125 3.394858 3.277125 2.711055 3.337820 3.337992 3.319293\r\n[36] 3.385678 3.457495 3.487009 3.278930 3.289835 3.388635 3.306040\r\n[43] 3.343629 3.358134 2.761787 3.271775 3.268790 2.590325 3.401460\r\n[50] 3.345771 3.297158 3.479707 3.325858 3.411842 3.446931 3.328759\r\n[57] 3.433447 3.282943\r\n\r\n\r\n\r\n\r\n",
    "preview": "posts/2022-10-07-entrega-ii-preparacion-de-los-datos/entrega-ii-preparacion-de-los-datos_files/figure-html5/unnamed-chunk-3-1.png",
    "last_modified": "2022-10-07T15:05:38-03:00",
    "input_file": {}
  },
  {
    "path": "posts/2022-09-23-tarea-clase-01-septiembre/",
    "title": "Tarea Clase 01 septiembre",
    "description": "Tarea de la clase del día 01 de septiembre del curso ICP5006-1 sobre gráficos exploratorios.",
    "author": [
      {
        "name": "Ines Pereira",
        "url": "https://example.com/norajones"
      }
    ],
    "date": "2022-09-23",
    "categories": [],
    "contents": "\r\nBase de datos\r\n\r\n\r\n#open database\r\nvdem <- readRDS(\"vdem.rds\")\r\nlibrary(tidyverse)\r\n#install.packages('sjmisc')\r\nlibrary(sjmisc)\r\n#install.packages('kableExtra')\r\nlibrary(kableExtra)\r\n\r\n#subset\r\nvdem_subset <- vdem %>% \r\n  select(country_name, v2x_partipdem, \r\n         v2x_cspart, v2elmulpar, v2psprlnks, e_peedgini, \r\n         e_regionpol, e_gdppc, e_pop) %>% \r\n  group_by(country_name) %>% \r\n  summarise_all(function(x)  mean(x, na.rm = T))\r\n\r\n\r\nHistograma\r\n\r\n\r\n#dependent variable\r\nvdem_subset %>% \r\n  ggplot(aes(x = v2x_cspart, na.rm = T)) +\r\n  geom_histogram(binwidth = 0.05) +\r\n  labs(x = \"Participación de las personas en OSC [0-1] \", y = \"Frecuencia\",\r\n       title = \"Distribución de la variable dependiente\",\r\n       caption = \"Fuente: Varieties of Democracy\")\r\n\r\n\r\n#independent variable\r\nvdem_subset %>% \r\n  ggplot(aes(x = e_peedgini, na.rm = T)) +\r\n  geom_histogram(binwidth = 2.5) +\r\n  labs(x = \"Coeficiente de Gini de desigualdad educacional\", y = \"Frecuencia\",\r\n       title = \"Distribución de la variable independiente\",\r\n       caption = \"Fuente: Varieties of Democracy\")\r\n\r\n\r\n\r\nGráfico de barras\r\n\r\n\r\nvdem_subset %>% \r\n  ggplot(aes(x=e_regionpol)) +\r\n  geom_bar(color=\"blue\", fill=\"white\") +\r\n  labs(x = \"Clasificación regional\", y = \"Frecuencia\",\r\n       title = \"Clasificación regional de los países basados en su posición política-geográfica\",\r\n       caption = \"Fuente: Varieties of Democracy\")\r\n\r\n\r\n\r\nBoxplot\r\n\r\n\r\nvdem_subset %>% \r\n  ggplot(aes(x=factor(e_regionpol), y = v2psprlnks  ))+\r\n  geom_boxplot( color=\"cadetblue\", fill=\"steelblue\", alpha = 0.5) +\r\n  theme_minimal() +\r\n  labs(x = \"Clasificacion Regional\", y = \"Forma de vínculo\"\",\r\n       title = \"Distribuicion de la forma de vínculo dos partidos y votantes por Clasificacion Regional\"\",\r\n       caption = \"Fuente: Varieties of Democracy\")\r\n\r\n\r\n\r\nScatterplot\r\n\r\n\r\nvdem_subset %>% \r\nggplot(aes(x=e_peedgini, y=v2x_cspart)) +\r\n  geom_point(color=\"cadetblue\", size=2, shape=23) + \r\n  labs(x = \"Inequidad educacional\", y = \"Participación de las personas en OSC \",\r\n       title = \"Relacion entre la Inequidad educacional y la Participación de las personas en OSC\",\r\n       caption = \"Fuente: Varieties of Democracy\")\r\n\r\n\r\n\r\n\r\n\r\n\r\n",
    "preview": "posts/2022-09-23-tarea-clase-01-septiembre/tarea-clase-01-septiembre_files/figure-html5/unnamed-chunk-2-1.png",
    "last_modified": "2022-09-23T17:21:48-03:00",
    "input_file": {}
  },
  {
    "path": "posts/2022-09-23-tarea-clase-08-septiembre/",
    "title": "Tarea Clase 08 septiembre",
    "description": "Tarea de la clase del día 08 de septiembre del curso ICP5006-1 sobre regresión lineal.",
    "author": [
      {
        "name": "Ines Pereira",
        "url": "https://example.com/norajones"
      }
    ],
    "date": "2022-09-23",
    "categories": [],
    "contents": "\r\nHipótesis\r\nLa inequidad educacional (Coeficiente Gini de Desigualdad Educativa)\r\ninfluye en la participación de partidos políticos en la competencia\r\nelectoral.\r\nVariable dependiente: participación de partidos políticos en la\r\ncompetencia electoral\r\nVariable independiente: inequidad educacional\r\nBase de datos\r\n\r\n\r\n#open database\r\nvdem <- readRDS(\"vdem.rds\")\r\nlibrary(tidyverse)\r\n#install.packages('sjmisc')\r\nlibrary(sjmisc)\r\n#install.packages('kableExtra')\r\nlibrary(kableExtra)\r\n\r\n#subset\r\nvdem_subset <- vdem %>% \r\n  select(country_name, v2x_partipdem, \r\n         v2x_cspart, v2elmulpar, v2psprlnks, e_peedgini, \r\n         e_regionpol, e_gdppc, e_pop) %>% \r\n  group_by(country_name) %>% \r\n  summarise_all(function(x)  mean(x, na.rm = T))\r\n\r\n\r\nModelo lineal simple\r\n\r\n\r\nmodelo_simple <- lm(v2elmulpar ~ 1 + e_peedgini, data = vdem_subset)\r\nclass(modelo_simple)\r\n\r\n[1] \"lm\"\r\n\r\nsummary(modelo_simple)\r\n\r\n\r\nCall:\r\nlm(formula = v2elmulpar ~ 1 + e_peedgini, data = vdem_subset)\r\n\r\nResiduals:\r\n     Min       1Q   Median       3Q      Max \r\n-2.64544 -0.63166  0.09447  0.73121  1.74730 \r\n\r\nCoefficients:\r\n            Estimate Std. Error t value Pr(>|t|)    \r\n(Intercept)  0.60762    0.17172   3.538 0.000556 ***\r\ne_peedgini  -0.01476    0.00319  -4.625 8.81e-06 ***\r\n---\r\nSignif. codes:  0 '***' 0.001 '**' 0.01 '*' 0.05 '.' 0.1 ' ' 1\r\n\r\nResidual standard error: 0.8837 on 132 degrees of freedom\r\n  (68 observations deleted due to missingness)\r\nMultiple R-squared:  0.1395,    Adjusted R-squared:  0.133 \r\nF-statistic: 21.39 on 1 and 132 DF,  p-value: 8.81e-06\r\n\r\n#install.packages(\"texreg\")\r\nlibrary(texreg)\r\nscreenreg(modelo_simple)\r\n\r\n\r\n=======================\r\n             Model 1   \r\n-----------------------\r\n(Intercept)    0.61 ***\r\n              (0.17)   \r\ne_peedgini    -0.01 ***\r\n              (0.00)   \r\n-----------------------\r\nR^2            0.14    \r\nAdj. R^2       0.13    \r\nNum. obs.    134       \r\n=======================\r\n*** p < 0.001; ** p < 0.01; * p < 0.05\r\n\r\nModelo lineal multiple\r\n\r\n\r\nmodelo_multiple <- lm(v2elmulpar ~ e_peedgini+e_regionpol , data = vdem_subset)\r\nclass(modelo_multiple)\r\n\r\n[1] \"lm\"\r\n\r\nsummary(modelo_multiple)\r\n\r\n\r\nCall:\r\nlm(formula = v2elmulpar ~ e_peedgini + e_regionpol, data = vdem_subset)\r\n\r\nResiduals:\r\n     Min       1Q   Median       3Q      Max \r\n-2.61306 -0.58126  0.08933  0.68341  1.75569 \r\n\r\nCoefficients:\r\n             Estimate Std. Error t value Pr(>|t|)    \r\n(Intercept)  0.416701   0.214304   1.944    0.054 .  \r\ne_peedgini  -0.015117   0.003185  -4.746 5.36e-06 ***\r\ne_regionpol  0.051976   0.035182   1.477    0.142    \r\n---\r\nSignif. codes:  0 '***' 0.001 '**' 0.01 '*' 0.05 '.' 0.1 ' ' 1\r\n\r\nResidual standard error: 0.8798 on 131 degrees of freedom\r\n  (68 observations deleted due to missingness)\r\nMultiple R-squared:  0.1536,    Adjusted R-squared:  0.1407 \r\nF-statistic: 11.88 on 2 and 131 DF,  p-value: 1.808e-05\r\n\r\nlibrary(texreg)\r\nscreenreg(modelo_multiple)\r\n\r\n\r\n=======================\r\n             Model 1   \r\n-----------------------\r\n(Intercept)    0.42    \r\n              (0.21)   \r\ne_peedgini    -0.02 ***\r\n              (0.00)   \r\ne_regionpol    0.05    \r\n              (0.04)   \r\n-----------------------\r\nR^2            0.15    \r\nAdj. R^2       0.14    \r\nNum. obs.    134       \r\n=======================\r\n*** p < 0.001; ** p < 0.01; * p < 0.05\r\n\r\nEvaluación de supuestos\r\nLinealidad de los parámetros\r\n\r\n\r\nggplot(mapping = aes(x = modelo_simple$fitted.values, y = modelo_simple$residuals)) +\r\n  labs(x = \"Valores predichos\", y = \"Residuos\") +\r\n  geom_point() +\r\n  geom_hline(mapping = aes(yintercept = 0), color = \"red\")\r\n\r\n\r\n\r\n\r\n\r\n\r\n",
    "preview": "posts/2022-09-23-tarea-clase-08-septiembre/tarea-clase-08-septiembre_files/figure-html5/unnamed-chunk-4-1.png",
    "last_modified": "2022-09-23T18:02:55-03:00",
    "input_file": {}
  },
  {
    "path": "posts/2022-09-08-entrega-i-introduccin-terica-del-proyecto/",
    "title": "Entrega I - Impacto de los cambios de los componentes ópticos oculares en la refracción de los jóvenes",
    "description": "En este post se presenta una introducción teórica del proyecto. Esta descripción presenta una introducción al tema y al problema a investigar, así como las variables que se estudiarán a lo largo del proyecto.",
    "author": [
      {
        "name": "Ines Pereira",
        "url": "https://example.com/norajones"
      }
    ],
    "date": "2022-09-08",
    "categories": [],
    "contents": "\r\nIntroducción\r\nLa presencia de la miopía en la población ha aumentado\r\nsignificativamente en las últimas décadas y se manifiesta de forma\r\nglobal. Las recientes predicciones de que la mitad de la población\r\nmundial será miope en 2050 resaltan la gran preocupación por los\r\nproblemas asociados a este aumento de la miopía. [1] Los valores\r\nelevados de miopía pueden provocar el desarrollo de complicaciones\r\noculares graves, entre las que destacan el desprendimiento de retina, el\r\nglaucoma y la catarata, habiendo indicios de ceguera en el futuro. [2],\r\n[3]\r\nHipótesis y variables\r\nLa progresión de la miopía se considera cuando un ojo miope corregido\r\npresenta variaciones en sus componentes ópticos oculares y enfoca los\r\nrayos de luz paralelos ante la retina. [4] Así, para estudiar el impacto\r\nde los cambios en los componentes ópticos oculares, como la longitud\r\naxial del ojo (CA) y el radio de curvatura (RC), en la refracción de los\r\njóvenes, se propone como hipótesis que la graduación de una persona\r\ndeterminada en su componente esférica (M) cambia con la longitud axial\r\ndel ojo (CA) y el radio de curvatura (RC).\r\nPara evaluar esta hipótesis, se recurre a una base de datos formada\r\npor las mediciones ópticas realizadas en una escuela, en Portugal. En\r\nesta base de datos se encuentran las siguientes variables:\r\nclase: clase de los alumnos en estudiovariable cualitativa\r\n\r\nnombre: nombre de los alumnos en estudiovariable cualitativa\r\n\r\nsexo: sexo de los alumnos en estudiovariable binaria1: masculino, 0: femenino\r\n\r\n\r\nametropia: defecto de refracciónvariable cualitativa ordinal: 3 niveles-1:miopia, 0: emetropia, 1:hipermetropia\r\n\r\n\r\nedad: edad de los alumnos en estudiovariable cuantitativa discreta\r\n\r\ngrupo_etario: grupo de edad de los alumnos en\r\nestudiovariable cualitativa ordinal: 3 niveles\r\n\r\nM: graduación de los alumnos en estudio determinada\r\nen su componente esféricavariable cuantitativa continua\r\n\r\nJ0: componente vectorial horizontal del\r\nastigmatismovariable cuantitativa continua\r\n\r\nJ45:componente vectorial oblicuo del\r\nastigmatismovariable cuantitativa continua\r\n\r\nesf: valor de la esfera de la refracción\r\nconvencionalvariable cuantitativa continua\r\n\r\ncil: valor del cilindro de la refracción\r\nconvencionalvariable cuantitativa continua\r\n\r\neje: valor del eje de la refracción\r\nconvencionalvariable cuantitativa continua\r\n\r\norient_astigm: orientación del astigmatismovariable cualitativa ordinal: 3 niveles\r\n\r\nCA: longitud axial del ojovariable cuantitativa continua\r\n\r\nRC: radio de curvaturavariable cuantitativa continua\r\n\r\nCA_RC: predictor del defecto de refracciónvariable cuantitativa continua<3: hipermetrope, 3: emetrope, >3:miope\r\n\r\n\r\nEn esto proyecto y con el objetivo de evaluar el impacto de los\r\ncambios de los componentes ópticos oculares en la refracción de los\r\njóvenes, se considerarán como variables independientes la longitud\r\naxial del ojo (CA) y el radio de curvatura (RC). La variable\r\ndependiente en estudio es la graduación de la persona en su\r\ncomponente esférica (M). Esta variable no se mide directamente, sino\r\nque se obtiene convirtiendo en equivalente esférico, a través de sus\r\ncomponentes del vector de refracción, los valores obtenidos en la\r\nrefracción del objetivo monocular. Estos valores son la esfera (Esf), el\r\ncilindro (Cil) y el eje (α) de la refracción convencional y se incluyen\r\nen las siguientes ecuaciones [5]:\r\nM = Esf + Cil/2\r\nJ0 = -Cil x cos (2 α)/2\r\nJ45 = -Cil x sin (2 α)/2\r\nDe este modo, midiendo estos valores y aplicando las ecuaciones\r\nmencionadas, se obtienen los valores de graduación deseados para poder\r\nevaluar el impacto de los componentes ópticos en este valor.\r\nConclusión\r\nFinalmente, con el estudio de estas variables se pretende evaluar los\r\ncambios en la graduación de los jóvenes con la progresión de la miopía,\r\nexpresada en la variación de la longitud del ojo y el radio de\r\ncurvatura.\r\nReferencias\r\n[1] Clin Exp Opto. 2015 Nov;98(6):491-3. doi: 10.1111/cxo.12339.\r\nNearly 1 billion myopes at risk of myopia-related sight-threatening\r\nconditions by 2050 - time to act now Brien A Holden, Monica Jong,\r\nStephen Davis, David Wilson, Tim Fricke, Serge Resnikoff\r\n[2] S. Hasebe, J. Jun, and S. R. Varnas, “Myopia control with\r\npositively aspherized progressive addition lenses: A 2-year,\r\nmulticenter, randomized, controlled trial,” Investig. Ophthalmol. Vis.\r\nSci., 2014, doi: 10.1167/iovs.12-11462.\r\n[3] B. A. Holden et al., “Global Prevalence of Myopia and High\r\nMyopia and Temporal Trends from 2000 through 2050,” Ophthalmology,\r\nvol. 123, no. 5. pp. 1036–1042, 2016, doi:\r\n10.1016/j.ophtha.2016.01.006.\r\n[4]\r\nTese de doutoramento António Queirós Pereira. Universidade do Minho.\r\n2011.\r\n[5] L. N. Thibos, W. Wheeler, and D. Horner, “Power vectors: an\r\napplication of Fourier analysis to the description and statistical\r\nanalysis of refractive error,” Optom Vis.Sci, vol. 74, no. 1040-5488\r\n(Print), pp. 367–375, Jun. 1997.\r\n\r\n\r\n\r\n",
    "preview": {},
    "last_modified": "2022-10-07T16:47:24-03:00",
    "input_file": {}
  },
  {
    "path": "posts/welcome/",
    "title": "Welcome to Clases Datos Politicos ",
    "description": "Welcome to our new blog, Clases Datos Politicos . We hope you enjoy \nreading what we have to say!",
    "author": [
      {
        "name": "Nora Jones",
        "url": "https://example.com/norajones"
      }
    ],
    "date": "2022-08-25",
    "categories": [],
    "contents": "\r\n\r\n\r\n\r\n",
    "preview": {},
    "last_modified": "2022-08-25T17:48:49-04:00",
    "input_file": {}
  }
]
